torch_find_peaks/__init__.py
torch_find_peaks/find_peaks.py
torch_find_peaks/gaussians.py
torch_find_peaks/py.typed
torch_find_peaks/refine_peaks.py
torch_find_peaks-0.0.1.dist-info/METADATA
torch_find_peaks-0.0.1.dist-info/WHEEL
torch_find_peaks-0.0.1.dist-info/licenses/LICENSE
torch_find_peaks-0.0.1.dist-info/RECORD
