Metadata-Version: 2.4
Name: torch-find-peaks
Version: 0.0.1
Summary: Peak finding and fitting using torch
Project-URL: homepage, https://github.com/jojoelfe/torch-find-peaks
Project-URL: repository, https://github.com/jojoelfe/torch-find-peaks
Author-email: Johannes Elferich <jojotux123@hotmail.com>
License: BSD-3-Clause
License-File: LICENSE
Classifier: Development Status :: 3 - Alpha
Classifier: License :: OSI Approved :: BSD License
Classifier: Programming Language :: Python :: 3
Classifier: Programming Language :: Python :: 3.10
Classifier: Programming Language :: Python :: 3.11
Classifier: Programming Language :: Python :: 3.12
Classifier: Programming Language :: Python :: 3.13
Classifier: Typing :: Typed
Requires-Python: >=3.10
Requires-Dist: mkdocs-jupyter>=0.25.1
Requires-Dist: mkdocs-material>=9.6.11
Requires-Dist: pandas>=2.2.3
Requires-Dist: torch-grid-utils>=0.0.1
Requires-Dist: torch-subpixel-crop>=0.0.3
Requires-Dist: torch>=2.6.0
Provides-Extra: dev
Requires-Dist: ipython; extra == 'dev'
Requires-Dist: mkdocs; extra == 'dev'
Requires-Dist: mkdocs-jupyter; extra == 'dev'
Requires-Dist: mkdocs-material; extra == 'dev'
Requires-Dist: mkdocstrings[python]; extra == 'dev'
Requires-Dist: mypy; extra == 'dev'
Requires-Dist: pdbpp; extra == 'dev'
Requires-Dist: pre-commit; extra == 'dev'
Requires-Dist: rich; extra == 'dev'
Requires-Dist: ruff; extra == 'dev'
Provides-Extra: test
Requires-Dist: pytest; extra == 'test'
Requires-Dist: pytest-cov; extra == 'test'
